calculator/__init__.py
calculator/calculator.py
Haleh_python_calculator-2.0.0.dist-info/METADATA
Haleh_python_calculator-2.0.0.dist-info/WHEEL
Haleh_python_calculator-2.0.0.dist-info/top_level.txt
Haleh_python_calculator-2.0.0.dist-info/RECORD
