Metadata-Version: 2.1
Name: Haleh-python-calculator
Version: 2.0.0
Summary: A lightweight and easy-to-use calculator package for Python
Home-page: https://github.com/TuringCollegeSubmissions/hkafas-DWWP.1
Author: Haleh Kafashinamdar
Author-email: halehnamdar@gmail.com
Classifier: Development Status :: 5 - Production/Stable
Classifier: Intended Audience :: Developers
Classifier: License :: OSI Approved :: MIT License
Classifier: Programming Language :: Python
Classifier: Programming Language :: Python :: 3
Classifier: Programming Language :: Python :: 3.6
Classifier: Programming Language :: Python :: 3.7
Classifier: Programming Language :: Python :: 3.8
Classifier: Programming Language :: Python :: 3.9
Requires-Python: >=3.6
